README.md
setup.py
yolov5_inference/__init__.py
yolov5_inference/infer.py
yolov5_inference.egg-info/PKG-INFO
yolov5_inference.egg-info/SOURCES.txt
yolov5_inference.egg-info/dependency_links.txt
yolov5_inference.egg-info/requires.txt
yolov5_inference.egg-info/top_level.txt
yolov5_inference/models/__init__.py
yolov5_inference/models/common.py
yolov5_inference/models/experimental.py
yolov5_inference/models/yolo.py
yolov5_inference/utils/__init__.py
yolov5_inference/utils/augmentations.py
yolov5_inference/utils/autoanchor.py
yolov5_inference/utils/datasets.py
yolov5_inference/utils/downloads.py
yolov5_inference/utils/general.py
yolov5_inference/utils/google_utils.py
yolov5_inference/utils/loss.py
yolov5_inference/utils/metrics.py
yolov5_inference/utils/plots.py
yolov5_inference/utils/torch_utils.py