Metadata-Version: 2.1
Name: yolov5-inference
Version: 0.7
Summary: code de inference yolov5
Home-page: https://github.com/ultralytics/yolov5
Author: cuongngm
Author-email: cuonghip0908@gmail.com
License: UNKNOWN
Platform: UNKNOWN
Classifier: Programming Language :: Python :: 3
Classifier: License :: OSI Approved :: MIT License
Classifier: Operating System :: OS Independent
Requires-Python: >=3.6
